django_sti_models/__init__.py
django_sti_models/admin.py
django_sti_models/exceptions.py
django_sti_models/fields.py
django_sti_models/management/__init__.py
django_sti_models/management/commands/__init__.py
django_sti_models/management/commands/validate_sti_models.py
django_sti_models/models.py
django_sti_models/utils.py
django_sti_models-0.1.45.dist-info/LICENSE
django_sti_models-0.1.45.dist-info/METADATA
django_sti_models-0.1.45.dist-info/WHEEL
django_sti_models-0.1.45.dist-info/RECORD
